vha_toolbox/__init__.py
vha_toolbox/data_manipulation.py
vha_toolbox/date_utils.py
vha_toolbox/ean.py
vha_toolbox/excel_column_conversion.py
vha_toolbox/file_hash_utils.py
vha_toolbox/format_size.py
vha_toolbox/frame_ratio_utils.py
vha_toolbox/highlight_text.py
vha_toolbox/image_crop_utils.py
vha_toolbox/isbn.py
vha_toolbox/magnet_link.py
vha_toolbox/sql_helper.py
vha_toolbox/string_manipulation.py
vha_toolbox/table_generator.py
vha_toolbox-0.0.15.dist-info/licenses/LICENSE
vha_toolbox-0.0.15.dist-info/METADATA
vha_toolbox-0.0.15.dist-info/WHEEL
vha_toolbox-0.0.15.dist-info/top_level.txt
vha_toolbox-0.0.15.dist-info/RECORD
