Metadata-Version: 2.4
Name: vha-toolbox
Version: 0.0.15
Summary: My personal Python toolbox
Home-page: https://github.com/VictorHachard/vha-toolbox
Author: Victor Hachard
Author-email: 31635811+VictorHachard@users.noreply.github.com
License: MIT
Project-URL: Source, https://github.com/VictorHachard/vha-toolbox
Project-URL: Bug Tracker, https://github.com/VictorHachard/vha-toolbox/issues
Classifier: Programming Language :: Python :: 3
Classifier: Programming Language :: Python :: 3 :: Only
Classifier: Programming Language :: Python :: 3.8
Classifier: Programming Language :: Python :: 3.9
Classifier: Programming Language :: Python :: 3.10
Classifier: Programming Language :: Python :: 3.11
Classifier: Programming Language :: Python :: 3.12
Classifier: Programming Language :: Python :: 3.13
Classifier: Programming Language :: Python :: 3.14
License-File: LICENSE
Requires-Dist: Unidecode==1.4.0
Requires-Dist: Pillow>=10.0.0
Dynamic: author
Dynamic: author-email
Dynamic: classifier
Dynamic: description
Dynamic: description-content-type
Dynamic: home-page
Dynamic: license
Dynamic: license-file
Dynamic: project-url
Dynamic: requires-dist
Dynamic: summary
